random_id/__init__.py
random_id/random_id.py
random_id-1.0.1.dist-info/COPYING.LESSER.txt
random_id-1.0.1.dist-info/COPYING.txt
random_id-1.0.1.dist-info/METADATA
random_id-1.0.1.dist-info/WHEEL
random_id-1.0.1.dist-info/top_level.txt
random_id-1.0.1.dist-info/RECORD
