Metadata-Version: 2.1
Name: random-id
Version: 1.0.1
Summary: A simple, flexible random ID generator.
Home-page: https://github.com/AlexiWolf/random_id
Author: AlexiWolf
Author-email: alexiwolf@pm.me
License: UNKNOWN
Platform: UNKNOWN
Classifier: Programming Language :: Python :: 3
Classifier: Programming Language :: Python :: 3.4
Classifier: Programming Language :: Python :: 3.5
Classifier: Programming Language :: Python :: 3.6
Classifier: Programming Language :: Python :: 3.7
Classifier: Programming Language :: Python :: 3.8
Classifier: License :: OSI Approved :: GNU Lesser General Public License v3 or later (LGPLv3+)
Classifier: Development Status :: 5 - Production/Stable
Requires-Python: >=3.5
